{
  "success_normal": {
    "success": true,
    "fallbackCode": null,
    "record_id": "rec_demo_001",
    "analysisId": "ana_demo_001",
    "record_status": "demo_mock_completed",
    "image_url": "/uploads/demo.jpg",
    "ai_source": "mock",
    "result": {
      "score": 86,
      "title": "今日发量守护者",
      "summary": "这张记录看起来清爽有精神，今天的头发小伙伴状态在线。",
      "task": {
        "name": "今晚早点睡",
        "description": "给头发小伙伴一点安静休息时间。",
        "exp_reward": 12
      },
      "growthDelta": {
        "exp_added": 12,
        "current_level": 1,
        "streak_days": 1
      },
      "tags": ["清爽", "稳定", "元气在线"],
      "disclaimer": "本结果仅用于娱乐和习惯记录，不构成医疗建议。",
      "roast": "发丝们开会很守秩序，没有上演离家出走大戏。",
      "encouragement": "继续轻松记录就好，保持这个节奏很适合 demo 展示。",
      "image_quality": "clear",
      "source": "mock",
      "source_label": "Demo mock 结果",
      "daily_task": "给头发小伙伴一点安静休息时间。",
      "count": "中等",
      "thickness": "正常",
      "suggestions": ["给头发小伙伴一点安静休息时间。"]
    }
  },
  "success_low_quality_saveable": {
    "success": true,
    "fallbackCode": "LOW_QUALITY_IMAGE",
    "record_id": "rec_demo_002",
    "analysisId": "ana_demo_002",
    "record_status": "demo_mock_saved_with_notes",
    "image_url": "/uploads/dark.jpg",
    "ai_source": "mock",
    "result": {
      "score": 58,
      "title": "模糊也努力奖",
      "summary": "图片有点暗或不够清楚，但这次记录已经成功保存。",
      "task": {
        "name": "拍照补光挑战",
        "description": "下次记录时找一盏温柔的灯帮忙。",
        "exp_reward": 8
      },
      "growthDelta": {
        "exp_added": 8,
        "current_level": 1,
        "streak_days": 1
      },
      "tags": ["已记录", "光线偏暗", "下次更清楚"],
      "disclaimer": "本结果仅用于娱乐和习惯记录，不构成医疗建议。",
      "roast": "镜头像刚睡醒，头发小伙伴也有点害羞。",
      "encouragement": "下次试试靠近一点、光线亮一点，结果页会更好看。",
      "image_quality": "low_light_or_blurry",
      "source": "mock",
      "source_label": "Demo mock 结果",
      "daily_task": "下次记录时找一盏温柔的灯帮忙。",
      "count": "中等",
      "thickness": "正常",
      "suggestions": ["下次记录时找一盏温柔的灯帮忙。"]
    }
  },
  "failed_fallback": {
    "success": false,
    "fallbackCode": "MOCK_ANALYSIS_FALLBACK",
    "record_id": "rec_demo_003",
    "analysisId": "ana_demo_003",
    "record_status": "demo_mock_fallback",
    "image_url": "/uploads/fail.jpg",
    "ai_source": "mock",
    "result": {
      "score": 50,
      "title": "发丝临时休息站",
      "summary": "这次分析暂时开小差了，但记录没有丢。",
      "task": {
        "name": "喝水打卡",
        "description": "先喝一杯水，给今天加一点轻松感。",
        "exp_reward": 5
      },
      "growthDelta": {
        "exp_added": 5,
        "current_level": 1,
        "streak_days": 1
      },
      "tags": ["已保存", "临时反馈", "稍后可重试"],
      "disclaimer": "本结果仅用于娱乐和习惯记录，不构成医疗建议。",
      "roast": "分析小机器人去倒水了，回来继续营业。",
      "encouragement": "不用担心，demo 场景会稳定返回可展示结果。",
      "image_quality": "unknown",
      "source": "mock",
      "source_label": "Demo mock 结果",
      "daily_task": "先喝一杯水，给今天加一点轻松感。",
      "count": "中等",
      "thickness": "正常",
      "suggestions": ["先喝一杯水，给今天加一点轻松感。"]
    }
  }
}
